<?xml version="1.0" encoding="utf-8"?>
<TextureAtlas>
	<Texture>SpriteSheets/Dungeon-Tileset</Texture>
	<Regions>
		<Region name="solid-cyan" x="984" y="11" width="16" height="16" />
		<Region name="block-tile" x="1001" y="11" width="16" height="16" />
		<Region name="statue-tile-1" x="1018" y="11" width="16" height="16" />
		<Region name="statue-tile-2" x="1035" y="11" width="16" height="16" />
		<Region name="solid-black" x="984" y="28" width="16" height="16" />
		<Region name="textured-tile" x="1001" y="28" width="16" height="16" />
		<Region name="stair-tile" x="1035" y="28" width="16" height="16" />
		<Region name="brick-tile" x="984" y="45" width="16" height="16" />
		<Region name="white-pattern-tile" x="1001" y="45" width="16" height="16" />

		<Region name="wall-west-bottom" x="521" y="115" width="32" height="72" />
		<Region name="wall-west-top" x="521" y="11" width="32" height="72" />
		<Region name="wall-east-bottom" x="745" y="115" width="32" height="72" />
		<Region name="wall-east-top" x="745" y="11" width="32" height="72" />

		<Region name="wall-south-left" x="553" y="155" width="80" height="32" />
		<Region name="wall-south-right" x="665" y="155" width="80" height="32" />
		<Region name="wall-north-left" x="553" y="11" width="80" height="32" />
		<Region name="wall-north-right" x="665" y="11" width="80" height="32" />

		<Region name="wall-tile-north" x="815" y="11" width="32" height="32" />
		<Region name="wall-tile-west" x="815" y="44" width="32" height="32" />
		<Region name="wall-tile-east" x="815" y="77" width="32" height="32" />
		<Region name="wall-tile-south" x="815" y="110" width="32" height="32" />

		<Region name="enterance-tile-north" x="848" y="11" width="32" height="32" />
		<Region name="enterance-tile-west" x="848" y="44" width="32" height="32" />
		<Region name="enterance-tile-east" x="848" y="77" width="32" height="32" />
		<Region name="enterance-tile-south" x="848" y="110" width="32" height="32" />

		<Region name="locked-door-tile-north" x="881" y="11" width="32" height="32" />
		<Region name="locked-door-tile-west" x="881" y="44" width="32" height="32" />
		<Region name="locked-door-tile-east" x="881" y="77" width="32" height="32" />
		<Region name="locked-door-tile-south" x="881" y="110" width="32" height="32" />

		<Region name="door-tile-north" x="914" y="11" width="32" height="32" />
		<Region name="door-tile-west" x="914" y="44" width="32" height="32" />
		<Region name="door-tile-east" x="914" y="77" width="32" height="32" />
		<Region name="door-tile-south" x="914" y="110" width="32" height="32" />

		<Region name="hole-in-wall-north" x="947" y="11" width="32" height="32" />
		<Region name="hole-in-wall-west" x="947" y="44" width="32" height="32" />
		<Region name="hole-in-wall-east" x="947" y="77" width="32" height="32" />
		<Region name="hole-in-wall-south" x="947" y="110" width="32" height="32" />
	</Regions>
	<Animations>
	</Animations>
</TextureAtlas>